{
  "hash": "9086e50c",
  "configHash": "2e50df3e",
  "lockfileHash": "c8767452",
  "browserHash": "72640f40",
  "optimized": {
    "react": {
      "src": "../../node_modules/react/index.js",
      "file": "react.js",
      "fileHash": "759e7cc6",
      "needsInterop": true
    },
    "react-dom/client": {
      "src": "../../node_modules/react-dom/client.js",
      "file": "react-dom_client.js",
      "fileHash": "4a1838e8",
      "needsInterop": true
    },
    "react-router-dom": {
      "src": "../../node_modules/react-router-dom/dist/index.mjs",
      "file": "react-router-dom.js",
      "fileHash": "5ccbf3f2",
      "needsInterop": false
    },
    "react-toastify": {
      "src": "../../node_modules/react-toastify/dist/index.mjs",
      "file": "react-toastify.js",
      "fileHash": "7f01c586",
      "needsInterop": false
    },
    "react-hook-form": {
      "src": "../../node_modules/react-hook-form/dist/index.esm.mjs",
      "file": "react-hook-form.js",
      "fileHash": "dc76b749",
      "needsInterop": false
    },
    "lucide-react": {
      "src": "../../node_modules/lucide-react/dist/esm/lucide-react.js",
      "file": "lucide-react.js",
      "fileHash": "1e734d26",
      "needsInterop": false
    },
    "react-icons/fa": {
      "src": "../../node_modules/react-icons/fa/index.mjs",
      "file": "react-icons_fa.js",
      "fileHash": "ee9a3684",
      "needsInterop": false
    },
    "@headlessui/react": {
      "src": "../../node_modules/@headlessui/react/dist/headlessui.esm.js",
      "file": "@headlessui_react.js",
      "fileHash": "0456ee27",
      "needsInterop": false
    },
    "@supabase/supabase-js": {
      "src": "../../node_modules/@supabase/supabase-js/dist/module/index.js",
      "file": "@supabase_supabase-js.js",
      "fileHash": "ab459a2c",
      "needsInterop": false
    }
  },
  "chunks": {
    "browser-VLKRZ7RP": {
      "file": "browser-VLKRZ7RP.js"
    },
    "chunk-C5A7FNJB": {
      "file": "chunk-C5A7FNJB.js"
    },
    "chunk-XE2STDAP": {
      "file": "chunk-XE2STDAP.js"
    },
    "chunk-2KHBIA62": {
      "file": "chunk-2KHBIA62.js"
    },
    "chunk-D2KY6O3O": {
      "file": "chunk-D2KY6O3O.js"
    },
    "chunk-V4OQ3NZ2": {
      "file": "chunk-V4OQ3NZ2.js"
    }
  }
}